MANIFEST.in
README
ez_setup.py
n.py
n.pyw
setup.py
nts/NTS.ico
nts/NTS_128.png
nts/NTS_256.png
nts/NTS_32.png
nts/__init__.py
nts/ntsData.py
nts/ntsDocs.py
nts/ntsRC.py
nts/ntsVersion.py
nts/ntsWX.py
nts.egg-info/PKG-INFO
nts.egg-info/SOURCES.txt
nts.egg-info/dependency_links.txt
nts.egg-info/top_level.txt