Metadata-Version: 1.0
Name: nts
Version: 78
Summary: note taking simplified
Home-page: http://www.duke.edu/~dgraham/NTS
Author: Daniel A Graham
Author-email: daniel.graham@duke.edu
License: License :: OSI Approved :: GNU General Public License (GPL)
Platform: Any
Classifier: Development Status :: 5 - Production/Stable
Classifier: Environment :: Console
Classifier: Intended Audience :: End Users/Desktop
Classifier: License :: OSI Approved :: GNU General Public License (GPL)
Classifier: Operating System :: OS Independent
Classifier: Programming Language :: Python
Classifier: Topic :: Utilities
Classifier: Topic :: Office/Business
